cm_adb/__init__.py
cm_adb/client.py
cm_adb/server.py
tests/__init__.py
tests/server_tests.py
cmadb-0.0.1.dist-info/LICENSE
cmadb-0.0.1.dist-info/METADATA
cmadb-0.0.1.dist-info/WHEEL
cmadb-0.0.1.dist-info/top_level.txt
cmadb-0.0.1.dist-info/RECORD
