Metadata-Version: 2.1
Name: cmadb
Version: 0.0.1
Summary: UNKNOWN
Home-page: UNKNOWN
Author: PunchyArchy
Author-email: ksmdrmvscthny@gmail.com
License: UNKNOWN
Platform: UNKNOWN
License-File: LICENSE
